zeusai/__init__.py
zeusai/zeusai.py
zeusai-0.1.1.dist-info/METADATA
zeusai-0.1.1.dist-info/WHEEL
zeusai-0.1.1.dist-info/top_level.txt
zeusai-0.1.1.dist-info/RECORD
